[
  {
    "title": "Web",
    "url": "/contents",
    "icon": "fa-regular fa-window-maximize",
    "fee": "Free"
  },
  {
    "title": "Apple Books",
    "url": "https://books.apple.com/us/book/proudly-serving/id6761822948",
    "icon": "fa-brands fa-apple",
    "fee": "Free"
  },
  {
    "title": "Google Play Books",
    "url": "https://play.google.com/store/books/details?id=Z2TMEQAAQBAJ&pli=1",
    "icon": "fa-brands fa-google-play",
    "fee": "Free"
  },
  {
    "title": "EPUB",
    "url": "/assets/docs/Proudly_Serving.epub",
    "icon": "fa-solid fa-file-alt",
    "fee": "Free"
  },
  {
    "title": "HTML",
    "url": "/assets/docs/proudly-serving.html",
    "icon": "fa-solid fa-file-code",
    "fee": "Free"
  }
]